setup.cfg
setup.py
dap/__init__.py
dap.responses.json.egg-info/PKG-INFO
dap.responses.json.egg-info/SOURCES.txt
dap.responses.json.egg-info/dependency_links.txt
dap.responses.json.egg-info/entry_points.txt
dap.responses.json.egg-info/namespace_packages.txt
dap.responses.json.egg-info/requires.txt
dap.responses.json.egg-info/top_level.txt
dap.responses.json.egg-info/zip-safe
dap/responses/__init__.py
dap/responses/json/__init__.py
